langgate/processor/__init__.py
langgate/processor/envoy_extproc.py
langgate/processor/ext_proc.py
langgate/processor/py.typed
langgate/processor/server.py
langgate_processor-0.3.3.dist-info/METADATA
langgate_processor-0.3.3.dist-info/WHEEL
langgate_processor-0.3.3.dist-info/RECORD
